spkrepo/__init__.py
spkrepo/app.py
spkrepo/cli.py
spkrepo/exceptions.py
spkrepo/ext.py
spkrepo/models.py
spkrepo/utils.py
spkrepo/static/css/bootstrap.min.css
spkrepo/static/css/spkrepo.css
spkrepo/static/fonts/glyphicons-halflings-regular.eot
spkrepo/static/fonts/glyphicons-halflings-regular.svg
spkrepo/static/fonts/glyphicons-halflings-regular.ttf
spkrepo/static/fonts/glyphicons-halflings-regular.woff
spkrepo/static/js/bootstrap.min.js
spkrepo/static/js/html5shiv.min.js
spkrepo/static/js/jquery-2.1.1.min.js
spkrepo/static/js/jquery.dotdotdot.min.js
spkrepo/static/js/respond.min.js
spkrepo/static/js/spkrepo.js
spkrepo/templates/_wtfhelpers.html
spkrepo/templates/base.html
spkrepo/templates/layout.html
spkrepo/templates/frontend/index.html
spkrepo/templates/frontend/package.html
spkrepo/templates/frontend/packages.html
spkrepo/templates/frontend/profile.html
spkrepo/templates/security/change_password.html
spkrepo/templates/security/forgot_password.html
spkrepo/templates/security/login_user.html
spkrepo/templates/security/register_user.html
spkrepo/templates/security/reset_password.html
spkrepo/templates/security/send_confirmation.html
spkrepo/tests/common.py
spkrepo/tests/test_admin.py
spkrepo/tests/test_api.py
spkrepo/tests/test_frontend.py
spkrepo/tests/test_nas.py
spkrepo/tests/test_utils.py
spkrepo/views/__init__.py
spkrepo/views/admin.py
spkrepo/views/api.py
spkrepo/views/frontend.py
spkrepo/views/nas.py
spkrepo-0.3.2.dist-info/METADATA
spkrepo-0.3.2.dist-info/WHEEL
spkrepo-0.3.2.dist-info/entry_points.txt
spkrepo-0.3.2.dist-info/licenses/LICENSE
spkrepo-0.3.2.dist-info/RECORD
