Metadata-Version: 2.4
Name: spkrepo
Version: 0.3.2
Summary: Synology Package Repository
Author-email: Antoine Bertin <diaoulael@gmail.com>
License-Expression: MIT
License-File: LICENSE
Keywords: package,repository,synology
Classifier: Development Status :: 5 - Production/Stable
Classifier: Environment :: Web Environment
Classifier: Framework :: Flask
Classifier: Intended Audience :: Developers
Classifier: Operating System :: OS Independent
Classifier: Programming Language :: Python :: 3.12
Classifier: Topic :: Internet :: WWW/HTTP :: Dynamic Content
Classifier: Topic :: Internet :: WWW/HTTP :: WSGI :: Application
Classifier: Topic :: System :: Archiving :: Packaging
Requires-Python: <4.0,>=3.12
Requires-Dist: alembic>=1.17.2
Requires-Dist: bcrypt>=5.0.0
Requires-Dist: click>=8.3.1
Requires-Dist: configparser>=7.2.0
Requires-Dist: flask-admin>=2.0.2
Requires-Dist: flask-babel>=4.0.0
Requires-Dist: flask-caching>=2.3.1
Requires-Dist: flask-debugtoolbar>=0.16.0
Requires-Dist: flask-mail>=0.10.0
Requires-Dist: flask-migrate>=4.1.0
Requires-Dist: flask-principal>=0.4.0
Requires-Dist: flask-restful>=0.3.10
Requires-Dist: flask-security>=5.7.1
Requires-Dist: flask-sqlalchemy>=3.1.1
Requires-Dist: flask-wtf>=1.2.2
Requires-Dist: flask>=3.1.2
Requires-Dist: pillow>=12.0.0
Requires-Dist: python-gnupg>=0.5.5
Requires-Dist: requests>=2.32.5
Requires-Dist: sqlalchemy>=2.0.45
Requires-Dist: wtforms>=3.2.1
